visium_stitcher/__init__.py
visium_stitcher-0.0.3.dist-info/LICENSE
visium_stitcher-0.0.3.dist-info/WHEEL
visium_stitcher-0.0.3.dist-info/METADATA
visium_stitcher-0.0.3.dist-info/RECORD
